{
  "doc": null,
  "immediate_dependencies": [
    {
      "address": "0000000000000000000000000000000000000000000000000000000000000000",
      "name": "registry"
    },
    {
      "address": "0000000000000000000000000000000000000000000000000000000000000000",
      "name": "userstate"
    },
    {
      "address": "0000000000000000000000000000000000000000000000000000000000000000",
      "name": "wal"
    },
    {
      "address": "0000000000000000000000000000000000000000000000000000000000000000",
      "name": "warlotsystem"
    },
    {
      "address": "0000000000000000000000000000000000000000000000000000000000000001",
      "name": "string"
    },
    {
      "address": "0000000000000000000000000000000000000000000000000000000000000002",
      "name": "balance"
    },
    {
      "address": "0000000000000000000000000000000000000000000000000000000000000002",
      "name": "clock"
    },
    {
      "address": "0000000000000000000000000000000000000000000000000000000000000002",
      "name": "coin"
    },
    {
      "address": "0000000000000000000000000000000000000000000000000000000000000002",
      "name": "object"
    },
    {
      "address": "0000000000000000000000000000000000000000000000000000000000000002",
      "name": "tx_context"
    }
  ],
  "attributes": [],
  "functions": {
    "create_user": {
      "source_index": 0,
      "index": 0,
      "doc": null,
      "attributes": [],
      "visibility": "Public",
      "entry": false,
      "type_parameters": [],
      "parameters": [
        {
          "name": "system_cfg",
          "type_": {
            "Reference": [
              true,
              {
                "Datatype": {
                  "module": {
                    "address": "0000000000000000000000000000000000000000000000000000000000000000",
                    "name": "warlotsystem"
                  },
                  "name": "SystemConfig",
                  "type_arguments": []
                }
              }
            ]
          }
        },
        {
          "name": "apikey",
          "type_": {
            "Datatype": {
              "module": {
                "address": "0000000000000000000000000000000000000000000000000000000000000001",
                "name": "string"
              },
              "name": "String",
              "type_arguments": []
            }
          }
        },
        {
          "name": "encrypt_key",
          "type_": {
            "Datatype": {
              "module": {
                "address": "0000000000000000000000000000000000000000000000000000000000000001",
                "name": "string"
              },
              "name": "String",
              "type_arguments": []
            }
          }
        },
        {
          "name": "warlot_sign_apikey",
          "type_": {
            "Datatype": {
              "module": {
                "address": "0000000000000000000000000000000000000000000000000000000000000001",
                "name": "string"
              },
              "name": "String",
              "type_arguments": []
            }
          }
        },
        {
          "name": "public_username",
          "type_": {
            "Datatype": {
              "module": {
                "address": "0000000000000000000000000000000000000000000000000000000000000001",
                "name": "string"
              },
              "name": "String",
              "type_arguments": []
            }
          }
        },
        {
          "name": "clock",
          "type_": {
            "Reference": [
              false,
              {
                "Datatype": {
                  "module": {
                    "address": "0000000000000000000000000000000000000000000000000000000000000002",
                    "name": "clock"
                  },
                  "name": "Clock",
                  "type_arguments": []
                }
              }
            ]
          }
        },
        {
          "name": "ctx",
          "type_": {
            "Reference": [
              true,
              {
                "Datatype": {
                  "module": {
                    "address": "0000000000000000000000000000000000000000000000000000000000000002",
                    "name": "tx_context"
                  },
                  "name": "TxContext",
                  "type_arguments": []
                }
              }
            ]
          }
        }
      ],
      "return_": []
    },
    "update_api_key": {
      "source_index": 1,
      "index": 1,
      "doc": null,
      "attributes": [],
      "visibility": "Public",
      "entry": false,
      "type_parameters": [],
      "parameters": [
        {
          "name": "system_cfg",
          "type_": {
            "Reference": [
              true,
              {
                "Datatype": {
                  "module": {
                    "address": "0000000000000000000000000000000000000000000000000000000000000000",
                    "name": "warlotsystem"
                  },
                  "name": "SystemConfig",
                  "type_arguments": []
                }
              }
            ]
          }
        },
        {
          "name": "registry",
          "type_": {
            "Reference": [
              true,
              {
                "Datatype": {
                  "module": {
                    "address": "0000000000000000000000000000000000000000000000000000000000000000",
                    "name": "registry"
                  },
                  "name": "Registry",
                  "type_arguments": []
                }
              }
            ]
          }
        },
        {
          "name": "new_hashed_apikey",
          "type_": {
            "Datatype": {
              "module": {
                "address": "0000000000000000000000000000000000000000000000000000000000000001",
                "name": "string"
              },
              "name": "String",
              "type_arguments": []
            }
          }
        },
        {
          "name": "new_warlot_sign_apikey",
          "type_": {
            "Datatype": {
              "module": {
                "address": "0000000000000000000000000000000000000000000000000000000000000001",
                "name": "string"
              },
              "name": "String",
              "type_arguments": []
            }
          }
        },
        {
          "name": "clock",
          "type_": {
            "Reference": [
              false,
              {
                "Datatype": {
                  "module": {
                    "address": "0000000000000000000000000000000000000000000000000000000000000002",
                    "name": "clock"
                  },
                  "name": "Clock",
                  "type_arguments": []
                }
              }
            ]
          }
        },
        {
          "name": "payment",
          "type_": {
            "Reference": [
              true,
              {
                "Datatype": {
                  "module": {
                    "address": "0000000000000000000000000000000000000000000000000000000000000002",
                    "name": "coin"
                  },
                  "name": "Coin",
                  "type_arguments": [
                    {
                      "Datatype": {
                        "module": {
                          "address": "0000000000000000000000000000000000000000000000000000000000000000",
                          "name": "wal"
                        },
                        "name": "WAL",
                        "type_arguments": []
                      }
                    }
                  ]
                }
              }
            ]
          }
        },
        {
          "name": "ctx",
          "type_": {
            "Reference": [
              true,
              {
                "Datatype": {
                  "module": {
                    "address": "0000000000000000000000000000000000000000000000000000000000000002",
                    "name": "tx_context"
                  },
                  "name": "TxContext",
                  "type_arguments": []
                }
              }
            ]
          }
        }
      ],
      "return_": []
    }
  },
  "structs": {},
  "enums": {}
}